Workbook
Name \C: #REF!
Name \C: #REF!
Name \D: #REF!
Name \D: #REF!
Name \E: #REF!
Name \E: #REF!
Name \P: #REF!
Name \P: #REF!
Name \U: #REF!
Name \U: #REF!
Name _\b: #N/A
Name _\C: #REF!
Name _\C: #REF!
Name _\D: #REF!
Name _\D: #REF!
Name _\E: #REF!
Name _\E: #REF!
Name _\f: #N/A
Name _\g: #N/A
Name _\GD: #N/A
Name _\h: #N/A
Name _\i: #N/A
Name _\j: #N/A
Name _\k: #N/A
Name _\l: #N/A
Name _\m: #N/A
Name _\n: #N/A
Name _\o: #N/A
Name _\P: #REF!
Name _\P: #REF!
Name _\q: #N/A
Name _\s: #N/A
Name _\U: #REF!
Name _\U: #REF!
Name _2.1: #REF!
Name _2.1: #REF!
Name _2.3.3: #REF!
Name _2.3.3: #REF!
Name _3.2.2: #REF!
Name _3.2.2: #REF!
Name _3.3: #REF!
Name _3.3: #REF!
Name _5.1: #REF!
Name _5.1: #REF!
Name _5.1.2: #REF!
Name _5.1.2: #REF!
Name _6.1.1: #REF!
Name _6.1.1: #REF!
Name _7.4: #REF!
Name _7.4: #REF!
Name _8.1.7: #REF!
Name _8.1.7: #REF!
Name _Regression_Int: 1
Name A: #REF!
Name A: #REF!
Name a_korek: #REF!
Name a_korek: #REF!
Name aA: NA()
Name AAAA: #REF!
Name AAAA: #REF!

Sheet MASTER
B3: RINCIAN PENAWARAN HARGA
B4: JASA SEWA ALAT BERAT PENDUKUNG OPERASIONAL SENORO DAN TIAKA
B5: No. | C5: Kategory | D5: Description | E5: Qty | F5: Unit | G5: Rate | H5: Unit Price | I5: Total Price | J5: No.2
B6: A | C6: MONTHLY BASIS | D6: - MONTHLY BASIS | E6: - | F6: - | G6: - | H6: - | J6: A
B7: 1 | C7: MONTHLY BASIS | D7: Jasa Sewa Alat Berat Monthly Basis (Include Operator, Rigger, Helper, BBM & Sertifikasi), Truck Mounted Crane (TMC) Capacity 8 T | E7: 36 | F7: Unit | G7: Month | H7: 131224000 | I7: =E7*H7 -> 4724064000 | J7: 1
B8: 2 | C8: MONTHLY BASIS | D8: Jasa Sewa Alat Berat Monthly Basis (Include Operator, Rigger, Helper, BBM & Sertifikasi), Man Lift Capacity 227 Kg | E8: 36 | F8: Unit | G8: Month | H8: 62818000 | I8: =E8*H8 -> 2261448000 | J8: 2
B9: 3 | C9: MONTHLY BASIS | D9: Jasa Sewa Alat Berat Monthly Basis (Include Operator, Rigger, Helper, BBM & Sertifikasi), Mobile Crane Capacity 80 T | E9: 36 | F9: Unit | G9: Month | H9: 189241000 | I9: =E9*H9 -> 6812676000 | J9: 3
B10: 4 | C10: MONTHLY BASIS | D10: Jasa Sewa Alat Berat Monthly Basis (Include Operator, Rigger, Helper, BBM & Sertifikasi), Backhoe Loader 70 - 100 HP | E10: 36 | F10: Unit | G10: Month | H10: 75538000 | I10: =E10*H10 -> 2719368000 | J10: 4
B11: 5 | C11: MONTHLY BASIS | D11: Jasa Sewa Alat Berat Monthly Basis (Include Operator, Rigger, Helper, BBM & Sertifikasi), Vacuum Truck 10.000 L | E11: 36 | F11: Unit | G11: Month | H11: 78225000 | I11: =E11*H11 -> 2816100000 | J11: 5
B12: B | C12: ON CALL BASIS | D12: - ON CALL BASIS | E12: - | F12: - | G12: - | H12: - | J12: B
B13: 1 | C13: ON CALL BASIS | D13: Jasa Sewa Alat Berat On Call Basis (Include Operator, Rigger, Helper, BBM & Sertifikasi), Dump Truck 4 Ton min 120PS | E13: 90 | F13: Unit | G13: Day | H13: 1936000 | I13: =E13*H13 -> 174240000 | J13: 1
B14: =B13+1 -> 2 | C14: ON CALL BASIS | D14: Jasa Sewa Alat Berat On Call Basis (Include Operator, Rigger, Helper, BBM & Sertifikasi), Excavator 130-150 HP | E14: 120 | F14: Unit | G14: Day | H14: 4746000 | I14: =E14*H14 -> 569520000 | J14: =J13+1 -> 2
B15: =B14+1 -> 3 | C15: ON CALL BASIS | D15: Jasa Sewa Alat Berat On Call Basis (Include Operator, Rigger, Helper, BBM & Sertifikasi), Motor Grader 100 - 200 HP | E15: 365 | F15: Unit | G15: Day | H15: 5340000 | I15: =E15*H15 -> 1949100000 | J15: =J14+1 -> 3
B16: =B15+1 -> 4 | C16: ON CALL BASIS | D16: Jasa Sewa Alat Berat On Call Basis (Include Operator, Rigger, Helper, BBM & Sertifikasi), Single Drum Compactor 10 Ton | E16: 365 | F16: Unit | G16: Day | H16: 4231000 | I16: =E16*H16 -> 1544315000 | J16: =J15+1 -> 4
B17: =B16+1 -> 5 | C17: ON CALL BASIS | D17: Jasa Sewa Alat Berat On Call Basis (Include Operator, Rigger, Helper, BBM & Sertifikasi), Tank Truck 5000 L | E17: 60 | F17: Unit | G17: Day | H17: 2215000 | I17: =E17*H17 -> 132900000 | J17: =J16+1 -> 5
B18: =B17+1 -> 6 | C18: ON CALL BASIS | D18: Jasa Sewa Alat Berat On Call Basis (Include Operator, Rigger, Helper, BBM & Sertifikasi), Additional Mobile Crane Capacity 80T (On Call) | E18: 10 | F18: Unit | G18: Month | H18: 210000000 | I18: =E18*H18 -> 2100000000 | J18: =J17+1 -> 6
B19: =B18+1 -> 7 | C19: ON CALL BASIS | D19: Jasa Sewa Alat Berat On Call Basis (Include Operator, Rigger, Helper, BBM & Sertifikasi), Mobile Crane Capacity 100T (On Call) | E19: 10 | F19: Unit | G19: Month | H19: 350000000 | I19: =E19*H19 -> 3500000000 | J19: =J18+1 -> 7
B20: =B19+1 -> 8 | C20: ON CALL BASIS | D20: Jasa Sewa Alat Berat On Call Basis (Include Operator, Rigger, Helper, BBM & Sertifikasi), Telehandler Capacity 5T (On Call) | E20: 5 | F20: Unit | G20: Month | H20: 80000000 | I20: =E20*H20 -> 400000000 | J20: =J19+1 -> 8
B21: =B20+1 -> 9 | C21: ON CALL BASIS | D21: Jasa Sewa Alat Berat On Call Basis (Include Operator, Rigger, Helper, BBM & Sertifikasi), Telehandler Capacity 3T (On Call) | E21: 5 | F21: Unit | G21: Month | H21: 75000000 | I21: =E21*H21 -> 375000000 | J21: =J20+1 -> 9
B22: C | C22: JASA MOBILISASI - DEMOBILISASI | D22: - JASA MOBILISASI - DEMOBILISASI | E22: - | F22: - | G22: - | H22: - | J22: C
B23: 1 | C23: JASA MOBILISASI - DEMOBILISASI | D23: Jasa Mob - Demob (Per Unit), Mobilisasi Semua Alat Berat Dari Luar Luwuk ke Luwuk (Monthly Basis) | E23: 1 | F23: Trip | G23: AU | H23: 400000000 | I23: =E23*H23 -> 400000000 | J23: 1
B24: 2 | C24: JASA MOBILISASI - DEMOBILISASI | D24: Jasa Mob - Demob (Per Unit), Demobilisasi Semua Alat Berat Dari Luar Luwuk ke Luwuk (Monthly Basis) | E24: 1 | F24: Trip | G24: AU | H24: 0 | I24: =E24*H24 -> 0 | J24: 2
B25: 3 | C25: JASA MOBILISASI - DEMOBILISASI | D25: Jasa Mob - Demob (Per Unit), Mobilisasi & Demobilisasi Alat Berat Crane dan Telehandler Dari Luar Luwuk ke Luwuk (On Call Basis) | E25: 12 | F25: Trip | G25: AU | H25: 300000000 | I25: =E25*H25 -> 3600000000 | J25: 3
B26: 4 | C26: JASA MOBILISASI - DEMOBILISASI | D26: Jasa Mob - Demob (Per Unit), Mobilisasi Untuk Alat Berat Diluar TMC, Vacuum Truck, Dump Truck & Tank Truck Dari Luwuk ke Senoro (Monthly dan On Call Basis) (Tronton/Trailer) | E26: 40 | F26: Trip | G26: AU | H26: 7500000 | I26: =E26*H26 -> 300000000 | J26: 4
B27: 5 | C27: JASA MOBILISASI - DEMOBILISASI | D27: Jasa Mob - Demob (Per Unit), Demobilisasi Untuk Alat Berat Diluar TMC, Vacuum Truck, Dump Truck & Tank Truck Dari Luwuk ke Senoro (Monthly dan On Call Basis) (Tronton/Trailer) | E27: 40 | F27: Trip | G27: AU | H27: 7500000 | I27: =E27*H27 -> 300000000 | J27: 5
B28: 6 | C28: JASA MOBILISASI - DEMOBILISASI | D28: Jasa Mob -- Demob (Per Unit), Mobilisasi dan Demobilisasi Alat berat Antar Lokasi Area Senoro Dengan Tronton / Trailer / Low Bed (Monthly dan On Call Basis) | E28: 22 | F28: Trip | G28: AU | H28: 8500000 | I28: =E28*H28 -> 187000000 | J28: 6
B29: D | C29: PROVISIONAL SUM | D29: - PROVISIONAL SUM | E29: - | F29: - | G29: - | H29: - | J29: D
B30: 1 | C30: PROVISIONAL SUM | D30: Miscellanious (Pekerjaan Khusus) | E30: 1 | F30: Lot | G30: Lot | H30: 3.8461707e+09 | I30: =E30*H30 -> 3.8461707e+09 | J30: 1

Sheet Input
B3: Input Database
B5: No | C5: Item | D5: Input
B6: 1 | C6: Contract No. | D6: 7207250142
B7: =B6+1 -> 2 | C7: Tender No | D7: S250551FLD-R1
B8: =B7+1 -> 3 | C8: Contract Title | D8: Jasa Sewa Alat Berat Pendukung Operasional Senoro dan Tiaka
B9: =B8+1 -> 4 | C9: Tanggal Contract | D9: 16 Desember 2025
B10: =B8+1 -> 4 | C10: Contract Period | D10: 24 Month
B11: =B10+1 -> 5 | C11: Proforma Invoice No. | D11: 042/BSS-JOB/AB/VII/2026
B12: =B11+1 -> 6 | C12: Tanggal Performa Invoice | D12: 46234
B13: =B12+1 -> 7 | C13: No PO | D13: 4500011424
B14: =B13+1 -> 8 | C14: Tanggal PO | D14: 46204
B15: =B14+1 -> 9 | C15: Keterangan PO | D15: “Jasa Sewa Backhoe Loader Untuk support Kegiatan Operation & Maintenance di Area Senoro dan Tiaka Periode Juli - September 2026, Refer CTR No. 7207250142-BSS-CTR-2026-019" (01 - 31 Juli 2026)
B16: =B15+1 -> 10 | C16: Pihak Pertama | D16: JOB Pertamina - Medco E&P Tomori Sulawesi
B17: =B16+1 -> 11 | C17: Alamat Pihak Pertama | D17: Bidakara Office Tower I 4Th Floor, Jl. Gatot Subroto Kav. 71 - 73, Jakarta 12870, Indonesia
B18: =B17+1 -> 12 | C18: Diwakili Oleh | D18: Ronny Dwi Purnomo / Rafik Hidayat
B19: =B18+1 -> 13 | C19: Selaku | D19: Maintenance Support Supervisor
B20: =B19+1 -> 14 | C20: Pihak Kedua | D20: PT Banggai Sentral Sulawesi
B21: =B20+1 -> 15 | C21: Alamat Pihak Kedua | D21: Jl. Urip Sumorharjo No. 53, Luwuk, Kabupaten Banggai, Provinsi Sulawesi Tengah (94715), Indonesia
B22: =B21+1 -> 16 | C22: Diwakili Oleh | D22: Ir. Ferry Tatimu
B23: =B22+1 -> 17 | C23: Selaku | D23: Director
B24: =B23+1 -> 18 | C24: Period | D24: 01 s/d 31 Juli 2026
B25: =B24+1 -> 19 | C25: Certificate No. (Cover WCC No.) | D25: 7207250142-BSS-WCC-2026-019
B26: =B25+1 -> 20 | C26: WCC Date | D26: 46234
B27: =B26+1 -> 21 | C27: WO No. | D27: 7207250142-BSS-WO-2026-019
B28: =B27+1 -> 22 | C28: WO Title | D28: Jasa Sewa Backhoe Loader untuk Support Kegiatan Operation dan Maintenance di Area Senoro dan Tiaka Periode Juli - September 2026 (01 - 31 Juli 2026)
B29: =B28+1 -> 23 | C29: CTR No. | D29: 7207250142-BSS-CTR-2026-019
B30: =B29+1 -> 24 | C30: Prepared by Name | D30: Onesimus Suriadi
B31: =B30+1 -> 25 | C31: Prepared by Tiltle | D31: General Service Manager
B32: =B31+1 -> 26
B33: =B32+1 -> 27
B34: =B33+1 -> 28
B35: =B34+1 -> 29
B36: =B35+1 -> 30
B37: =B36+1 -> 31
B38: =B37+1 -> 32
B39: =B38+1 -> 33

Sheet WCC Form
E4: JASA SEWA ALAT BERAT PENDUKUNG OPERASIONAL SENORO & TIAKA
E5: Contract No. 7207250142
C7: PT. BANGGAI SENTRAL SULAWESI
C9: WORK COMPLETION CERTIFICATE
C10: ="CERTIFICATE NO : "&Input!D25 -> CERTIFICATE NO : 7207250142-BSS-WCC-2026-019
C12: =CONCATENATE(L12," ",M13, " ",M14, " ",M15, " ",N12) -> On the date of 31 July 2026 we on behalf of PT Banggai Sentral Sulawesi have completed the following job: | L12: On the date of | M12: =Input!D26 -> 46234 | N12: we on behalf of PT Banggai Sentral Sulawesi have completed the following job:
M13: =DAY(M12) -> 31
C14: WORK ORDER NUMBER | D14: : | E14: =Input!D27 -> 7207250142-BSS-WO-2026-019 | M14: =TEXT(M12,"MMMM") -> July
C15: WORK ORDER TITLE | D15: : | E15: =Input!D28 -> Jasa Sewa Backhoe Loader untuk Support Kegiatan Operation dan Maintenance di Area Senoro dan Tiaka Periode Juli - September 2026 (01 - 31 Juli 2026) | M15: =YEAR(M12) -> 2026
C16: CTR NUMBER | D16: : | E16: =Input!D29 -> 7207250142-BSS-CTR-2026-019
C17: DESCRIPTION | D17: : | E17: ☑ Penyelesaian Pekerjaan | G17: ='Performa Invoice'!$K$19 -> 75538000
C18: AMOUNT TOTAL | D18: : | E18: =PROPER([1]!terbilang(G17) & " Rupiah ") -> Tujuh Puluh Lima Juta Lima Ratus Tiga Puluh Delapan Ribu Rupiah
C20: The work has been properly completed as per requirement, witnessed and accepted by JOB Pertamina - Medco E&P Tomori Sulawesi.
C25: Paisubololi, | D25: =Input!D26 -> 46234
C26: PT Banggai Sentral Sulawesi | F26: JOB Pertamina - Medco E&P Tomori Sulawesi
C27: Prepared by, | F27: Reviewed by, | G27: Approved by,
C29: Onesimus Suriadi | F29: Ronny Dwi Purnomo / Rafik Hidayat | G29: Imron Maulana / Moh Bazarul
C30: General Service Manager | F30: Maintenance Support Supervisor | G30: Field Senior Manager
F52: Ronny Dwi Purnomo / Rafik Hidayat | G52: Imron Maulana / Moh Bazarul
F53: Rafik Hidayat / Ronny Dwi Purnomo | G53: Moh Bazarul / Imron Maulana
F55: Maintenance Support Supervisor | G55: Maintenance Support Supervisor
F56: Maintenance Superintendent | G56: Field Senior Manager

Sheet Performa Invoice
B4: PT. BANGGAI SENTRAL SULAWESI
B5: Proforma Invoice
B8: TO | D8: =Input!D16 -> JOB Pertamina - Medco E&P Tomori Sulawesi | I8: PI No | J8: =Input!D11 -> 042/BSS-JOB/AB/VII/2026
D9: =Input!D17 -> Bidakara Office Tower I 4Th Floor, Jl. Gatot Subroto Kav. 71 - 73, Jakarta 12870, Indonesia | I9: Date | J9: =Input!D12 -> 46234
I10: Contract No | J10: =Input!D6 -> 7207250142
I11: Contract Duration | J11: =Input!D10 -> 24 Month
B12: Attn | D12: Attn. : Accounts Payable - Finance Department
B15: Item | C15: Description | E15: Qty | F15: Unit | G15: Duration | H15: Unit | I15: Percent | J15: Unit Price (IDR) | K15: TOTAL (IDR)
B16: a | C16: b | E16: c | F16: d | G16: e | H16: f | I16: g | J16: h | K16: i=c×e×h
B17: ='Rincian Pek'!B17 -> MONTHLY BASIS
B18: 1 | C18: ='Rincian Pek'!C17 -> Jasa Sewa Alat Berat Monthly Basis (Include Operator, Rigger, Helper, BBM & Sertifikasi), Backhoe Loader 70 - 100 HP | E18: ='Rincian Pek'!D17 -> 1 | F18: ='Rincian Pek'!E17 -> Unit | G18: ='Rincian Pek'!J17 -> 1 | H18: ='Rincian Pek'!K17 -> Month | I18: 1 | J18: ='Rincian Pek'!L17 -> 75538000 | K18: =E18*G18*I18*J18 -> 75538000
B19: Total | K19: =K18 -> 75538000
B21: Terbilang | D21: =PROPER([1]!terbilang(K19) & " Rupiah " ) -> Tujuh Puluh Lima Juta Lima Ratus Tiga Puluh Delapan Ribu Rupiah
B23: PAYMENT INSTRUCTION | I23: PT. BANGGAI SENTRAL SULAWESI
B24: Please remit to our bank:
B25: Account Name | D25: T. BANGGAI SENTRAL SULAWESI
B26: Bank Name | D26: BANK RAKYAT INDONESIA (PERSERO) Tbk.
B27: Branch | D27: Cabang Luwuk
B28: Account No | D28: 0167 0167 8888 303
I29: Onesimus Suriadi
I30: General Service Manager

Sheet Opname
A3: BERITA ACARA PEKERJAAN / OPNAME
B4: PT. BANGGAI SENTRAL SULAWESI
A7: DATE | C7: =Input!D12 -> 46234
A8: CTR No. | C8: =Input!D29 -> 7207250142-BSS-CTR-2026-019
A9: WO No. | C9: =Input!D27 -> 7207250142-BSS-WO-2026-019
A10: TITLE OF WORK ORDER | C10: =Input!D28 -> Jasa Sewa Backhoe Loader untuk Support Kegiatan Operation dan Maintenance di Area Senoro dan Tiaka Periode Juli - September 2026 (01 - 31 Juli 2026)
A12: NILAI KONTRAK (CTR) | D12: KUMULATIF LALU (PREVIOUS) | G12: AKTUAL OPNAME (BULAN INI) | K12: SISA ANGGARAN (DEVIASI)
A13: =G20 -> 226614000 | D13: =I20 -> 0 | G13: =K20 -> 75538000 | K13: =O20 -> 151076000
A16: NO. | B16: ITEM - DESCRIPTION | C16: Qty-Unit | D16: Uom | E16: BASE ON CTR | H16: PREVIOUS OPNAME | J16: AKTUAL OPNAME | L16: CUMMULATIVE OPNAME | N16: DEVIASI
E17: Volume | F17: Unit Price | G17: Price | H17: Volume | I17: Total Price | J17: Volume | K17: Total Price | L17: Volume | M17: Total Price | N17: Volume | O17: Total Price
A18: 1.1 | B18: ='Rincian Pek'!C17 -> Jasa Sewa Alat Berat Monthly Basis (Include Operator, Rigger, Helper, BBM & Sertifikasi), Backhoe Loader 70 - 100 HP | C18: 1 | D18: Month | E18: 3 | F18: 75538000 | G18: =E18*F18 -> 226614000 | H18: 0 | I18: =H18*F18 -> 0 | J18: ='Rincian Pek'!J17 -> 1 | K18: ='Rincian Pek'!L17 -> 75538000 | L18: =H18+J18 -> 1 | M18: =I18+K18 -> 75538000 | N18: =E18-L18 -> 2 | O18: =G18-M18 -> 151076000
B20: TOTAL | C20: =SUM(C18) -> 1 | D20: Month | E20: =SUM(E18) -> 3 | F20: 131224000 | G20: =SUM(G18) -> 226614000 | H20: =SUM(H18) -> 0 | I20: =SUM(I18) -> 0 | J20: =SUM(J18) -> 1 | K20: =SUM(K18) -> 75538000 | L20: =SUM(L18) -> 1 | M20: =SUM(M18) -> 75538000 | N20: =SUM(N18) -> 2 | O20: =SUM(O18) -> 151076000
A23: Catatan / Notes:
B24: PT. BANGGAI SENTRAL SULAWESI | G24: JOB PERTAMINA - MEDCO E&P TOMORI SULAWESI
B25: Prepared by, | G25: Reviewed by, | L25: Approved by,
B29: Onesimus Suriadi | G29: =Input!D18 -> Ronny Dwi Purnomo / Rafik Hidayat | L29: Imron Maulana / Moh Bazarul
B30: Manager General Services | G30: Maintenance Support Supervisor | L30: Field Senior Manager

Sheet Rincian Pek
A2: PT.BANGGAI SENTRAL SULAWESI
A3: Jl.Urip Sumoharjo No 53 Luwuk, Kabupaten Banggai, Propinsi Sulawesi Tengah
A7: RINCIAN PEKERJAAN
A8: Rincian Pekerjaan | C8: =Input!D25 -> 7207250142-BSS-WCC-2026-019 | H8: Ditujukan Kepada | K8: =Input!D16 -> JOB Pertamina - Medco E&P Tomori Sulawesi
A9: Nomor Kontrak | C9: =Input!D6 -> 7207250142 | H9: Nomor PO | K9: =Input!D13 -> 4500011424
A10: Nama Kontrak | C10: =Input!D8 -> Jasa Sewa Alat Berat Pendukung Operasional Senoro dan Tiaka | H10: Descripton PO | K10: =Input!D15 -> “Jasa Sewa Backhoe Loader Untuk support Kegiatan Operation & Maintenance di Area Senoro dan Tiaka Periode Juli - September 2026, Refer CTR No. 7207250142-BSS-CTR-2026-019" (01 - 31 Juli 2026)
A11: Nomor Tender | C11: =Input!D7 -> S250551FLD-R1 | H11: Tanggal PO | K11: =Input!D14 -> 46204
A12: Tanggal Proforma | C12: =Input!D12 -> 46234 | H12: Mata Uang | K12: IDR
A14: No. | B14: Kategori | C14: Spesifikasi / Deskripsi | D14: Out | E14: Unit | F14: Tanggal | J14: Aktual | L14: Harga Satuan (Rp) | M14: Total Harga (Rp) | N14: Keterangan Pekerjaan | P14: TKDN Komponen Jasa | T14: KOMPONEN BUKAN BIAYA | V14: KLN Komponen Jasa
F15: Tgl Mulai | G15: Tgl Selesai | H15: Out | I15: Unit | J15: Out | K15: Unit | P15: Biaya Bahan (Material) Terpakai | Q15: Biaya Tenaga Kerja & Konsultan | R15: Biaya Alat Kerja/Fasilitas Kerja | S15: Biaya Jasa Umum | V15: Biaya Bahan (Material) Terpakai | W15: Biaya Tenaga Kerja & Konsultan | X15: Biaya Alat Kerja/Fasilitas Kerja | Y15: Biaya Jasa Umum
A16: Column1 | B16: Column2 | C16: Column3 | D16: Column4 | E16: Column5 | F16: Column6 | G16: Column7 | H16: Column8 | I16: Column9 | J16: Column10 | K16: Column11 | L16: Column12 | M16: Column13 | N16: Column14
A17: 1 | B17: MONTHLY BASIS | C17: Jasa Sewa Alat Berat Monthly Basis (Include Operator, Rigger, Helper, BBM & Sertifikasi), Backhoe Loader 70 - 100 HP | D17: 1 | E17: Unit | F17: 46204 | G17: 46234 | H17: =Table3[[#This Row],[Column7]]-Table3[[#This Row],[Column6]]+1 -> 31 | I17: =IF(E17="","","Days") -> Days | J17: 1 | K17: Month | L17: =VLOOKUP(Table3[[#This Row],[Column3]],Table8[[Description]:[Total Price]],5,0) -> 75538000 | M17: =L17*J17 -> 75538000 | N17: Alat Beroperasi Periode 01 sd 31 Juli 2026 | P17: ='Rekap biaya'!R16*50/100*Table3[[#This Row],[Column10]] -> 11400000 | Q17: =('Rekap biaya'!S16+'Rekap biaya'!T16)*Table3[[#This Row],[Column10]] -> 21349217 | R17: =('Rekap biaya'!N16+'Rekap biaya'!Q16+'Rekap biaya'!X16+'Rekap biaya'!Y16)*Table3[[#This Row],[Column10]] -> 22821778 | S17: =('Rekap biaya'!U16+'Rekap biaya'!V16+'Rekap biaya'!W16)*Table3[[#This Row],[Column10]] -> 1172500 | T17: =('Rekap biaya'!O16*50/100)*Table3[[#This Row],[Column10]] -> 3697000 | V17: =('Rekap biaya'!R16*5/100)*Table3[[#This Row],[Column10]] -> 1140000 | X17: =('Rekap biaya'!R16*5%)*Table3[[#This Row],[Column10]] -> 1140000
P18: =Table3[[#This Row],[Column13]]*5% -> 0 | Q18: =Table3[[#This Row],[Column13]]*10% -> 0 | R18: ='Rekap biaya'!R16*40/100*J17 -> 9120000 | S18: =Table3[[#This Row],[Column13]]*3% -> 0 | T18: =Table3[[#This Row],[Column13]]*2/100 -> 0 | V18: =Table3[[#This Row],[Column13]]*5/100 -> 0
A19: TOTAL TAGIHAN | M19: =SUM(M17:M18) -> 75538000 | N19: =SUM(N17:N18) -> 0 | R19: =('Rekap biaya'!O16*50/100)*J17 -> 3697000
B21: Tebilang : | C21: #NAME? | P21: =SUM(P17:P19) -> 11400000 | Q21: =SUM(Q17:Q19) -> 21349217 | R21: =SUM(R17:R19) -> 35638778 | S21: =SUM(S17:S19) -> 1172500 | T21: =SUM(T17:T19) -> 3697000 | U21: =SUM(U17:U19) -> 0 | V21: =SUM(V17:V19) -> 1140000 | W21: =SUM(W17:W19) -> 0 | ... Y21: =SUM(Y17:Y19) -> 0
A23: AUTHORITY PT.BANGGAI SENTRAL SULAWESI | P23: =SUM(P21:Y21) -> 75537495 | Q23: =M19-P23 -> 504.88889
A24: DIBUAT OLEH | H24: DIPERIKSA | P24: =ROUNDUP(P21,-1) -> 11400000 | Q24: =ROUNDUP(Q21,-1) -> 21349220 | R24: =ROUNDUP(R21,-1) -> 35638780 | S24: =ROUNDUP(S21,-1) -> 1172500 | T24: =ROUNDUP(T21,-1) -> 3697000 | U24: =ROUNDUP(U21,-1) -> 0 | V24: =ROUNDUP(V21,-1) -> 1140000 | W24: =ROUNDUP(W21,-1) -> 0 | ... Y24: =ROUNDUP(Y21,-1) -> 0
C25: =OFFSET(Helper!$B$1,0,MATCH(B17,Helper!$A:$A,0)-1,COUNTA(OFFSET(Helper!$B$1,0,MATCH(B17,Helper!$A:$A,0)-1,1000,1)),1) | P25: =SUM(P24:Y24) -> 75537500 | Q25: =M19-P25 -> 500 | W25: =SUM(W17:W24) -> 0 | X25: =SUM(X17:X24) -> 3420000
A28: ( Yanuar Wiranata / Ireine Langi ) | H28: Onesimus Suriadi
A29: Supervisor | H29: Manager General Services
L30: ( Yanuar Wiranata / Ireine Langi )
L31: ( Ireine Langi / Yanuar Wiranata)

Sheet TKDN
A3: PT BANGGAI SENTRAL SULAWESI
A4: General Contractor and Suppliers
A8: TABEL PERHITUNGAN TINGKAT KOMPONEN DALAM NEGERI - JASA
A9: SELF - ASSESSMENT
B11: Nomor Kontrak | D11: =Input!D6 -> 7207250142
B12: Judul Kontrak | D12: =Input!D8 -> Jasa Sewa Alat Berat Pendukung Operasional Senoro dan Tiaka
B14: Nomor PO | D14: =Input!D13 -> 4500011424
B15: Nama Penyedia Barang / Jasa | D15: =Input!D20 -> PT Banggai Sentral Sulawesi
A17: A. Komponen Biaya (Cost Component) | D17: Mata Uang | E17: Perincian Nilai Biaya (Cost Summary) | H17: TKDN
E18: KDN | F18: KLN | G18: TOTAL | H18: % | I18: Nilai TKDN
B19: a | E19: b | F19: c | G19: d = b + c | H19: e = b / d | I19: f = d x e
A20: I. | B20: Biaya Bahan (Material) Terpakai | D20: Rp | E20: ='Rincian Pek'!P24 -> 11400000 | F20: ='Rincian Pek'!V24 -> 1140000 | G20: =SUM(E20:F20) -> 12540000 | H20: =IF(G20>0, E20/G20, 0) -> 0.90909091 | I20: =G20*H20 -> 11400000
B21: (material used cost) | D21: US$ | G21: =SUM(E21:F21) -> 0 | H21: =IF(G21>0, E21/G21, 0) -> 0 | I21: =G21*H21 -> 0
A22: II. | B22: Biaya Tenaga Kerja & Konsultan | D22: Rp | E22: ='Rincian Pek'!Q24 -> 21349220 | F22: ='Rincian Pek'!W24 -> 0 | G22: =SUM(E22:F22) -> 21349220 | H22: =IF(G22>0, E22/G22, 0) -> 1 | I22: =G22*H22 -> 21349220
B23: (personnel & consultant cost) | D23: US$ | G23: =SUM(E23:F23) -> 0 | H23: =IF(G23>0, E23/G23, 0) -> 0 | I23: =G23*H23 -> 0
A24: III. | B24: Biaya Alat Kerja / Fasilitas Kerja | D24: Rp | E24: ='Rincian Pek'!R24 -> 35638780 | F24: ='Rincian Pek'!X24 -> 1140000 | G24: =SUM(E24:F24) -> 36778780 | H24: =IF(G24>0, E24/G24, 0) -> 0.96900387 | I24: =G24*H24 -> 35638780
B25: (equipment & work facility cost) | D25: US$ | G25: =SUM(E25:F25) -> 0 | H25: =IF(G25>0, E25/G25, 0) -> 0 | I25: =G25*H25 -> 0
A26: IV. | B26: Biaya Jasa Umum | D26: Rp | E26: ='Rincian Pek'!S24 -> 1172500 | F26: ='Rincian Pek'!Y22 -> 0 | G26: =SUM(E26:F26) -> 1172500 | H26: =IF(G26>0, E26/G26, 0) -> 1 | I26: =G26*H26 -> 1172500
B27: (other services cost) | D27: US$ | G27: =SUM(E27:F27) -> 0 | H27: =IF(G27>0, E27/G27, 0) -> 0 | I27: =G27*H27 -> 0
A28: V. | B28: JUMLAH BIAYA (Σ I s/d IV) | D28: Rp | E28: =SUM(E20,E22,E24,E26) -> 69560500 | F28: =SUM(F20,F22,F24,F26) -> 2280000 | G28: =SUM(G20,G22,G24,G26) -> 71840500 | H28: =IF(G28>0, E28/G28, 0) -> 0.96826303 | I28: =G28*H28 -> 69560500
B29: (Total Cost) (Σ I s/d IV) | D29: US$ | E29: =SUM(E21,E23,E25,E27) -> 0 | F29: =SUM(F21,F23,F25,F27) -> 0 | G29: =SUM(G21,G23,G25,G27) -> 0 | H29: =IF(G29>0, E29/G29, 0) -> 0 | I29: =G29*H29 -> 0
A30: B. | B30: KOMPONEN BUKAN BIAYA | D30: Rp | G30: ='Rincian Pek'!T24+'Rincian Pek'!Q25 -> 3697500
B31: (Non-cost Component) | D31: US$
A32: C. | B32: JUMLAH NILAI | D32: Rp | G32: =G28+G30 -> 75538000
B33: (Total Value) | D33: US$ | G33: =G29+G31 -> 0
G34: =G32-'Rincian Pek'!M19 -> 0
B35: Catatan:
B36: • Isi hanya pada kolom yang berwarna kuning pastel.
B37: • Formulasi perhitungan mengacu pada Permen ESDM No. 15 Tahun 2013.
G39: Luwuk, 06 Juni 2026
G40: PT. Banggai Sentral Sulawesi
G45: Ir. Ferry Tatimu
G46: Direktur
A48: Head Office: Jl. Urip Sumoharjo 53, Luwuk 94715, Phone: 0461-21025, 21185, 21307, Fax: 0461-325241, email: Luwuk@ptbss.com
A49: Representative Office: Jl. Nginden Intan Tengah Blok F1- 47, Surabaya 60118, Phone : 031-5925721

Sheet BAMP
A2: BERITA ACARA MULAI PEKERJAAN (BAMP)
A6: =$O$6 -> Pada hari ini Rabu tanggal 1 bulan July tahun 2026 yang bertanda tangan di bawah ini: | O6: =CONCATENATE(O8, " ",P8, " ",O9, " ",P9, " ",O10, " ",P10, " ",O11, " ",P11, " ",O12) -> Pada hari ini Rabu tanggal 1 bulan July tahun 2026 yang bertanda tangan di bawah ini:
A8: 01. PIHAK PERTAMA | K8: tanggal / bulan / tahun | M8: Convert | O8: Pada hari ini | P8: =$N$9 -> Rabu
B9: Nama Perusahaan | C9: =Input!D16 -> JOB Pertamina - Medco E&P Tomori Sulawesi | K9: 46204 | L9: 1 | M9: =TEXT(K9,"dddd") -> Wednesday | N9: =VLOOKUP(M9,$M$10:$N$16,2,0) -> Rabu | O9: tanggal | P9: =DAY(K9) -> 1
B10: Alamat | C10: =Input!D17 -> Bidakara Office Tower I 4Th Floor, Jl. Gatot Subroto Kav. 71 - 73, Jakarta 12870, Indonesia | K10: REFERENSI PELAKSANAAN PEKERJAAN : | L10: 2 | M10: Sunday | N10: Minggu | O10: bulan | P10: =TEXT(K9,"MMMM") -> July
B11: Diwakili oleh | C11: =Input!D18 -> Ronny Dwi Purnomo / Rafik Hidayat | K11: Nomor Kontrak. | L11: 3 | M11: Monday | N11: Senin | O11: tahun | P11: =YEAR(K9) -> 2026 | U11: Tanggal Kontrak
B12: Jabatan | C12: =Input!D19 -> Maintenance Support Supervisor | K12: Nomor Purchase Order | L12: 4 | M12: Tuesday | N12: Selasa | O12: yang bertanda tangan di bawah ini: | U12: Tanggal Purchase Order
K13: Nomor Surat Perintah Kerja | L13: 5 | M13: Wednesday | N13: Rabu | U13: Tanggal Surat Perintah Kerja
A14: 02. PIHAK KEDUA | K14: Nomor Service Order | L14: 6 | M14: Thursday | N14: Kamis | U14: Tanggal Services Order
B15: Nama Perusahaan | C15: =Input!D20 -> PT Banggai Sentral Sulawesi | K15: Nomor Work Order | L15: 7 | M15: Friday | N15: Jum'at | U15: Tanggal Work Order
B16: Alamat | C16: =Input!D21 -> Jl. Urip Sumorharjo No. 53, Luwuk, Kabupaten Banggai, Provinsi Sulawesi Tengah (94715), Indonesia | K16: Nomor Surat Penawaran | L16: 8 | M16: Saturday | N16: Sabtu | U16: Tanggal Surat Penawaran
B17: Diwakili oleh | C17: =Input!D22 -> Ir. Ferry Tatimu | K17: Email | U17: Tanggal Email
B18: Jabatan | C18: Direktur | K18: WhatSapp | U18: Tanggal WhatSapp
K19: ----- | U19: -----
A20: DASAR PELAKSANAAN PEKERJAAN
B21: Referensi | C21: Nomor Kontrak. | D21: =Input!D6 -> 7207250142 | F21: Nomor Purchase Order | H21: =Input!D13 -> 4500011424
C22: Tanggal Kontrak | D22: =Input!D9 -> 16 Desember 2025 | F22: Tanggal Purchase Order | H22: =Input!D14 -> 46204
B24: Lingkup Pekerjaan | C24: =Input!D15 -> “Jasa Sewa Backhoe Loader Untuk support Kegiatan Operation & Maintenance di Area Senoro dan Tiaka Periode Juli - September 2026, Refer CTR No. 7207250142-BSS-CTR-2026-019" (01 - 31 Juli 2026)
A25: Dengan ini PIHAK KEDUA memulai melaksanakan pekerjaan dengan rincian sebagai berikut:
A26: NO | B26: KETERANGAN PEKERJAAN | D26: JUMLAH | F26: SATUAN | G26: CATATAN
A27: 1 | B27: ='Rincian Pek'!C17 -> Jasa Sewa Alat Berat Monthly Basis (Include Operator, Rigger, Helper, BBM & Sertifikasi), Backhoe Loader 70 - 100 HP | D27: ='Rincian Pek'!J17 -> 1 | F27: Unit | G27: Mulai Operasi Tanggal 01 Juli 2026
A30: Demikian Berita Acara Mulai Pekerjaan ini dibuat dan ditandatangani oleh kedua belah pihak untuk dipergunakan sebagaimana mestinya.
A38: PIHAK PERTAMA | F38: PIHAK KEDUA
A39: JOB Pertamina - Medco E&P Tomori Sulawesi | F39: PT Banggai Sentral Sulawesi
A43: =C11 -> Ronny Dwi Purnomo / Rafik Hidayat | F43: Ir. Ferry Tatimu
A44: =C12 -> Maintenance Support Supervisor | F44: Direktur
A48: Dokumen No: FM-GS-15 Rev:03
C49: Ir. Ferry Tatimu | F49: Aldito Fauzi Roe / Aryanto Yoga
C50: Onesimus Suriadi | F50: Aryanto Yoga / Aldito Fauzi Roe
C51: Direktur
C52: Manager General Services

Sheet BASP
A2: BERITA ACARA SELESAI PEKERJAAN (BASP)
A6: =$O$6 -> Pada hari ini Jum'at tanggal 31 bulan July tahun 2026 yang bertanda tangan di bawah ini: | O6: =CONCATENATE(O8, " ",P8, " ",O9, " ",P9, " ",O10, " ",P10, " ",O11, " ",P11, " ",O12) -> Pada hari ini Jum'at tanggal 31 bulan July tahun 2026 yang bertanda tangan di bawah ini:
A8: 01. PIHAK PERTAMA | K8: tanggal / bulan / tahun | M8: Convert | O8: Pada hari ini | P8: =$N$9 -> Jum'at
B9: Nama Perusahaan | C9: =Input!D16 -> JOB Pertamina - Medco E&P Tomori Sulawesi | K9: 46234 | L9: 1 | M9: =TEXT(K9,"dddd") -> Friday | N9: =VLOOKUP(M9,$M$10:$N$16,2,0) -> Jum'at | O9: tanggal | P9: =DAY(K9) -> 31
B10: Alamat | C10: =Input!D17 -> Bidakara Office Tower I 4Th Floor, Jl. Gatot Subroto Kav. 71 - 73, Jakarta 12870, Indonesia | K10: REFERENSI PELAKSANAAN PEKERJAAN : | L10: 2 | M10: Sunday | N10: Minggu | O10: bulan | P10: =TEXT(K9,"MMMM") -> July
B11: Diwakili oleh | C11: =Input!D18 -> Ronny Dwi Purnomo / Rafik Hidayat | K11: Nomor Kontrak. | L11: 3 | M11: Monday | N11: Senin | O11: tahun | P11: =YEAR(K9) -> 2026 | U11: Tanggal Kontrak
B12: Jabatan | C12: =Input!D19 -> Maintenance Support Supervisor | K12: Nomor Purchase Order | L12: 4 | M12: Tuesday | N12: Selasa | O12: yang bertanda tangan di bawah ini: | U12: Tanggal Purchase Order
K13: Nomor Surat Perintah Kerja | L13: 5 | M13: Wednesday | N13: Rabu | U13: Tanggal Surat Perintah Kerja
A14: 02. PIHAK KEDUA | K14: Nomor Service Order | L14: 6 | M14: Thursday | N14: Kamis | U14: Tanggal Services Order
B15: Nama Perusahaan | C15: =Input!D20 -> PT Banggai Sentral Sulawesi | K15: Nomor Work Order | L15: 7 | M15: Friday | N15: Jum'at | U15: Tanggal Work Order
B16: Alamat | C16: =Input!D21 -> Jl. Urip Sumorharjo No. 53, Luwuk, Kabupaten Banggai, Provinsi Sulawesi Tengah (94715), Indonesia | K16: Nomor Surat Penawaran | L16: 8 | M16: Saturday | N16: Sabtu | U16: Tanggal Surat Penawaran
B17: Diwakili oleh | C17: =Input!D22 -> Ir. Ferry Tatimu | K17: Email | U17: Tanggal Email
B18: Jabatan | C18: Direktur | K18: WhatSapp | U18: Tanggal WhatSapp
K19: ----- | U19: -----
A20: DASAR PELAKSANAAN PEKERJAAN
B21: Referensi | C21: Nomor Kontrak. | D21: =Input!D6 -> 7207250142 | F21: Nomor Purchase Order | H21: =Input!D13 -> 4500011424
C22: Tanggal Kontrak | D22: =Input!D9 -> 16 Desember 2025 | F22: Tanggal Purchase Order | H22: =Input!D14 -> 46204
B24: Lingkup Pekerjaan | C24: =Input!D15 -> “Jasa Sewa Backhoe Loader Untuk support Kegiatan Operation & Maintenance di Area Senoro dan Tiaka Periode Juli - September 2026, Refer CTR No. 7207250142-BSS-CTR-2026-019" (01 - 31 Juli 2026)
A25: Dengan ini PIHAK KEDUA telah selesai melaksanakan pekerjaan dengan rincian sebagai berikut:
A26: NO | B26: KETERANGAN PEKERJAAN | D26: JUMLAH | F26: SATUAN | G26: CATATAN
A27: 1 | B27: ='Rincian Pek'!C17 -> Jasa Sewa Alat Berat Monthly Basis (Include Operator, Rigger, Helper, BBM & Sertifikasi), Backhoe Loader 70 - 100 HP | D27: ='Rincian Pek'!J17 -> 1 | F27: ='Rincian Pek'!K17 -> Month | G27: Operasi Periode 01 sd 31 Juli 2026
A30: Demikian Berita Acara Selesai Pekerjaan ini dibuat dan ditandatangani oleh kedua belah pihak untuk dipergunakan sebagaimana mestinya.
A38: PIHAK PERTAMA | F38: PIHAK KEDUA
A39: JOB Pertamina - Medco E&P Tomori Sulawesi | F39: PT Banggai Sentral Sulawesi
A43: =C11 -> Ronny Dwi Purnomo / Rafik Hidayat | F43: Ir. Ferry Tatimu
A44: =C12 -> Maintenance Support Supervisor | F44: Direktur
A48: Dokumen No: FM-GS-14 Rev:03
C49: Ir. Ferry Tatimu | F49: Aldito Fauzi Roe / Aryanto Yoga
C50: Onesimus Suriadi | F50: Aryanto Yoga / Aldito Fauzi Roe
C51: Direktur
C52: Manager General Services

Sheet Heavy Equipment
C3: PT. BANGGAI SENTRAL SULAWESI JL. URIP SUMOHARJO NO. 53. TELP 0461-21025, 21185, 21307. LUWUK
C6: REKAP TIME SHEET PERALATAN
C8: Customer / User | N8: : | O8: =Input!D16 -> JOB Pertamina - Medco E&P Tomori Sulawesi
C9: Kontrak / SO No. | N9: : | O9: =Input!D6 -> 7207250142
C10: Proyek | N10: : | O10: =Input!D8 -> Jasa Sewa Alat Berat Pendukung Operasional Senoro dan Tiaka
C11: Sub Pekerjaan | N11: : | O11: =Input!D15 -> “Jasa Sewa Backhoe Loader Untuk support Kegiatan Operation & Maintenance di Area Senoro dan Tiaka Periode Juli - September 2026, Refer CTR No. 7207250142-BSS-CTR-2026-019" (01 - 31 Juli 2026)
C12: Periode | N12: : | O12: =Input!D24 -> 01 s/d 31 Juli 2026
C14: Date | N14: 1 | O14: 2 | P14: =O14+1 -> 3 | Q14: =P14+1 -> 4 | R14: =Q14+1 -> 5 | S14: =R14+1 -> 6 | T14: =S14+1 -> 7 | U14: =T14+1 -> 8 | V14: =U14+1 -> 9 | W14: =V14+1 -> 10 | ... AR14: =AQ14+1 -> 31 | AS14: TOTAL
C15: No | E15: Nomor Alat / Status | AS15: O | AT15: S | AU15: R | AV15: M
C16: 1 | E16: Jasa Sewa Alat Berat Monthly Basis (include operator,rigger,helper, maintenance, BBM & sertifikasi) | AY16: Jasa Sewa Alat Berat On Call Basis (include operator,rigger,helper, maintenance, BBM & sertifikasi)
C17: 1.1 | E17: Boom Truck ( TMC ) 8 ton | N17: S | O17: S | P17: O | Q17: S | R17: O | S17: O | T17: O | U17: O | V17: O | W17: O | X17: O | Y17: O | Z17: O | AA17: O | AB17: S | AC17: S | AD17: S | AE17: S | AF17: O | AG17: O | AH17: O | AI17: O | AJ17: S | AK17: S | AL17: O | AM17: S | AN17: S | AO17: O | AP17: S | AQ17: O | AR17: S | AS17: =COUNTIF(N17:AR17, "O") -> 18 | AT17: =COUNTIF(N17:AR17, "S") -> 13 | AU17: =COUNTIF(N17:AR17, "R") -> 0 | AV17: =COUNTIF(N17:AR17, "M") -> 0
AS18: =COUNTIF(N18:AR18, "O") -> 0 | AT18: =COUNTIF(N18:AR18, "S") -> 0 | AU18: =COUNTIF(N18:AR18, "R") -> 0 | AV18: =COUNTIF(N18:AR18, "M") -> 0
AS19: =COUNTIF(N19:AR19, "O") -> 0 | AT19: =COUNTIF(N19:AR19, "S") -> 0 | AU19: =COUNTIF(N19:AR19, "R") -> 0 | AV19: =COUNTIF(N19:AR19, "M") -> 0
E22: KODE STATUS : | N22: O | O22: Operation | R22: S | S22: Standby | V22: R | W22: Perbaikan | Z22: M | AA22: Mobilisasi | AM22: GRAND TOTAL | AS22: =SUM(AS16:AS20) -> 18 | AT22: =SUM(AT16:AT20) -> 13 | AU22: =SUM(AU16:AU20) -> 0 | AV22: =SUM(AV16:AV20) -> 0
C24: NOTE : | W24: User | AJ24: PT, Banggai Sentral Sulawesi
AJ25: Dibuat | AN25: Diperiksa | AR25: Disetujui
AJ31: Elvira Sutrisno | AN31: Ireine Langi | AR31: Onesimus Suriadi
B34: FM-GS-06 Rev.03
AJ36: Elvira Sutrisno | AO36: Ireine Langi | AS36: Onesimus Suriadi
AJ37: Nur Afiata | AO37: Yanuar Wiranata | AS37: Yanuar Wiranata
AJ38: Komang Andi | AO38: Nur Afiata
AJ39: Handry Panggato | AO39: Handry Panggato

Sheet Rekap biaya
A8: RINCIAN PENAWARAN HARGA
A9: Tender No S210104/JOBT/FLD, Jasa Sewa Alat Berat Pendukung Operasional Senoro | O9: 0.14
A10: NO | B10: DESCRIPTION | F10: QTY ITEM | G10: SATUAN | J10: PRICE ( IDR ) | K10: TOTAL PRICE ( IDR ) | L10: HARGA PENAWARAN SUDAH TERMASUK PROFIT | M10: TOTAL BIAYA OPERASIONAL | N10: LEMBUR | O10: Profit dari Biaya Operasional | P10: HPP BIAYA OPERASIONAL | Q10: Harga Sewa | R10: BIAYA OPERASIONAL ( sesuai lampiran ) | Z10: TOTAL
R11: BIAYA BBM | S11: TTL TUNJANGAN | T11: UPAH TENAGA KERJA | U11: MCU | V11: APD | W11: SERTIFIKASI | X11: TENGKI SOLAR DAN MOBIL OPERASIONAL DAN PORTACAMP | Y11: SERVICES DAN PEMELIHARAAN
A12: A. | B12: Jasa Sewa Alat Berat Monthly Basis (include operator,rigger,helper, maintenance, BBM & sertifikasi) | L12: E=A+D | M12: D= B+C | O12: C = B*25% | P12: B | R12: E | S12: C+D | T12: A | U12: F | V12: F | W12: G | X12: H | Y12: H | AA12: Jasa | AB12: Jasa + Fee | AC12: Barang | AD12: Barang + fee
A13: 1 | B13: Boom Truck Tronton 8 Ton | F13: 36 | G13: MON | H13: =J13-I13 -> 0 | I13: 131224000 | J13: =L13 -> 131224000 | K13: =F13*J13 -> 4724064000 | L13: =M13+Q13 -> 131224000 | M13: =ROUNDUP(O13+P13,-3)+N13 -> 108889000 | N13: 10713000 | O13: =ROUNDUP(P13*$O$9,-3) -> 12057000 | P13: =Z13 -> 86118034 | Q13: 22335000 | R13: 45600000 | S13: 14043000 | T13: 15693784 | U13: 687500 | V13: 758750 | W13: 1263888.9 | X13: 6210000 | Y13: 1861111.1 | Z13: =SUM(R13:Y13) -> 86118034 | AA13: =SUM(S13:Y13) -> 40518034 | AB13: =ROUNDUP((AA13*$O$9)+AA13,-3) -> 46191000 | AC13: =R13 -> 45600000 | AD13: =ROUNDUP((AC13*$O$9)+AC13,-3) -> 51984000
A14: 2 | B14: Man lift Capacity 227 kg | F14: 36 | G14: MON | H14: =J14-I14 -> 0 | I14: 62818000 | J14: =L14 -> 62818000 | K14: =F14*J14 -> 2261448000 | L14: =M14+Q14 -> 62818000 | M14: =ROUNDUP(O14+P14,-3)+N14 -> 43567000 | N14: 0 | O14: =ROUNDUP(P14*$O$9,-3) -> 5351000 | P14: =Z14 -> 38215884 | Q14: 19251000 | R14: 7600000 | S14: 10013000 | T14: 11491217 | U14: 458333.33 | V14: 505833.33 | W14: 333333.33 | X14: 6210000 | Y14: 1604166.7 | Z14: =SUM(R14:Y14) -> 38215884 | AA14: =SUM(S14:Y14) -> 30615884 | AB14: =ROUNDUP((AA14*$O$9)+AA14,-3) -> 34903000 | AC14: =R14 -> 7600000 | AD14: =ROUNDUP((AC14*$O$9)+AC14,-3) -> 8664000
A15: 3 | B15: Mobile Crane 70T - 80T | F15: 36 | G15: MON | H15: =J15-I15 -> 0 | I15: 189241000 | J15: =L15 -> 189241000 | K15: =F15*J15 -> 6812676000 | L15: =M15+Q15 -> 189241000 | M15: =ROUNDUP(O15+P15,-3)+N15 -> 88574000 | N15: 15449000 | O15: =ROUNDUP(P15*$O$9,-3) -> 8981000 | P15: =Z15 -> 64143694 | Q15: 100667000 | R15: 15200000 | S15: 14663000 | T15: 16849444 | U15: 687500 | V15: 758750 | W15: 1386111.1 | X15: 6210000 | Y15: 8388888.9 | Z15: =SUM(R15:Y15) -> 64143694 | AA15: =SUM(S15:Y15) -> 48943694 | AB15: =ROUNDUP((AA15*$O$9)+AA15,-3) -> 55796000 | AC15: =R15 -> 15200000 | AD15: =ROUNDUP((AC15*$O$9)+AC15,-3) -> 17328000
A16: 4 | B16: Backhoe Loader 70 - 100 HP | F16: 36 | G16: MON | H16: =J16-I16 -> 0 | I16: 75538000 | J16: =L16 -> 75538000 | K16: =F16*J16 -> 2719368000 | L16: =M16+Q16 -> 75538000 | M16: =ROUNDUP(O16+P16,-3)+N16 -> 60204000 | N16: 0 | O16: =ROUNDUP(P16*$O$9,-3) -> 7394000 | P16: =Z16 -> 52809495 | Q16: 15334000 | R16: 22800000 | S16: 9858000 | T16: 11491217 | U16: 458333.33 | V16: 505833.33 | W16: 208333.33 | X16: 6210000 | Y16: 1277777.8 | Z16: =SUM(R16:Y16) -> 52809495 | AA16: =SUM(S16:Y16) -> 30009495 | AB16: =ROUNDUP((AA16*$O$9)+AA16,-3) -> 34211000 | AC16: =R16 -> 22800000 | AD16: =ROUNDUP((AC16*$O$9)+AC16,-3) -> 25992000
A17: 5 | B17: Vacuum Truck 10.000 L | F17: 36 | G17: MON | H17: =J17-I17 -> 0 | I17: 78225000 | J17: =L17 -> 78225000 | K17: =F17*J17 -> 2816100000 | L17: =M17+Q17 -> 78225000 | M17: =ROUNDUP(O17+P17,-3)+N17 -> 58357000 | N17: 6386000 | O17: =ROUNDUP(P17*$O$9,-3) -> 6383000 | P17: =Z17 -> 45587273 | Q17: 19868000 | R17: 15200000 | S17: 9858000 | T17: 11491217 | U17: 458333.33 | V17: 505833.33 | W17: 208333.33 | X17: 6210000 | Y17: 1655555.6 | Z17: =SUM(R17:Y17) -> 45587273 | AA17: =SUM(S17:Y17) -> 30387273 | AB17: =ROUNDUP((AA17*$O$9)+AA17,-3) -> 34642000 | AC17: =R17 -> 15200000 | AD17: =ROUNDUP((AC17*$O$9)+AC17,-3) -> 17328000
B18: SUB TOTAL A | K18: =SUM(K13:K17) -> 19333656000 | L18: =SUM(L13:L17) -> 537046000 | M18: =SUM(M13:M17) -> 359591000 | O18: =SUM(O13:O17) -> 40166000 | P18: =SUM(P13:P17) -> 286874380 | Q18: =SUM(Q13:Q17) -> 177455000 | R18: =SUM(R13:R17) -> 106400000 | S18: =SUM(S13:S17) -> 58435000 | T18: =SUM(T13:T17) -> 67016880 | U18: =SUM(U13:U17) -> 2750000 | V18: =SUM(V13:V17) -> 3035000 | ... AD18: =SUM(AD13:AD17) -> 121296000
R19: 0 | S19: 0 | T19: 0 | U19: 0 | V19: 0 | W19: 0

Sheet Helper
A1: MONTHLY BASIS | B1: Jasa Sewa Alat Berat Monthly Basis (Include Operator, Rigger, Helper, BBM & Sertifikasi), Truck Mounted Crane (TMC) Capacity 8 T | C1: Jasa Sewa Alat Berat On Call Basis (Include Operator, Rigger, Helper, BBM & Sertifikasi), Dump Truck 4 Ton min 120PS | D1: Jasa Mob - Demob (Per Unit), Mobilisasi Semua Alat Berat Dari Luar Luwuk ke Luwuk (Monthly Basis) | E1: Miscellanious (Pekerjaan Khusus)
A2: ON CALL BASIS | B2: Jasa Sewa Alat Berat Monthly Basis (Include Operator, Rigger, Helper, BBM & Sertifikasi), Man Lift Capacity 227 Kg | C2: Jasa Sewa Alat Berat On Call Basis (Include Operator, Rigger, Helper, BBM & Sertifikasi), Excavator 130-150 HP | D2: Jasa Mob - Demob (Per Unit), Demobilisasi Semua Alat Berat Dari Luar Luwuk ke Luwuk (Monthly Basis)
A3: JASA MOBILISASI - DEMOBILISASI | B3: Jasa Sewa Alat Berat Monthly Basis (Include Operator, Rigger, Helper, BBM & Sertifikasi), Mobile Crane Capacity 80 T | C3: Jasa Sewa Alat Berat On Call Basis (Include Operator, Rigger, Helper, BBM & Sertifikasi), Motor Grader 100 - 200 HP | D3: Jasa Mob - Demob (Per Unit), Mobilisasi & Demobilisasi Alat Berat Crane dan Telehandler Dari Luar Luwuk ke Luwuk (On Call Basis)
A4: PROVISIONAL SUM | B4: Jasa Sewa Alat Berat Monthly Basis (Include Operator, Rigger, Helper, BBM & Sertifikasi), Backhoe Loader 70 - 100 HP | C4: Jasa Sewa Alat Berat On Call Basis (Include Operator, Rigger, Helper, BBM & Sertifikasi), Single Drum Compactor 10 Ton | D4: Jasa Mob - Demob (Per Unit), Mobilisasi Untuk Alat Berat Diluar TMC, Vacuum Truck, Dump Truck & Tank Truck Dari Luwuk ke Senoro (Monthly dan On Call Basis) (Tronton/Trailer)
B5: Jasa Sewa Alat Berat Monthly Basis (Include Operator, Rigger, Helper, BBM & Sertifikasi), Vacuum Truck 10.000 L | C5: Jasa Sewa Alat Berat On Call Basis (Include Operator, Rigger, Helper, BBM & Sertifikasi), Tank Truck 5000 L | D5: Jasa Mob - Demob (Per Unit), Demobilisasi Untuk Alat Berat Diluar TMC, Vacuum Truck, Dump Truck & Tank Truck Dari Luwuk ke Senoro (Monthly dan On Call Basis) (Tronton/Trailer)
C6: Jasa Sewa Alat Berat On Call Basis (Include Operator, Rigger, Helper, BBM & Sertifikasi), Additional Mobile Crane Capacity 80T (On Call) | D6: Jasa Mob -- Demob (Per Unit), Mobilisasi dan Demobilisasi Alat berat Antar Lokasi Area Senoro Dengan Tronton / Trailer / Low Bed (Monthly dan On Call Basis)
C7: Jasa Sewa Alat Berat On Call Basis (Include Operator, Rigger, Helper, BBM & Sertifikasi), Mobile Crane Capacity 100T (On Call)
C8: Jasa Sewa Alat Berat On Call Basis (Include Operator, Rigger, Helper, BBM & Sertifikasi), Telehandler Capacity 5T (On Call)
C9: Jasa Sewa Alat Berat On Call Basis (Include Operator, Rigger, Helper, BBM & Sertifikasi), Telehandler Capacity 3T (On Call)
